django_instagram/__init__.py
django_instagram/scraper.py
django_instagram/settings.py
django_instagram/static/django_instagram/css/slider.css
django_instagram/static/django_instagram/css/wall.css
django_instagram/static/django_instagram/js/slider.js
django_instagram/static/django_instagram/js/masonry/masonry.pkgd.js
django_instagram/static/django_instagram/js/masonry/masonry.pkgd.min.js
django_instagram/templates/django_instagram/recent_media_box.html
django_instagram/templates/django_instagram/recent_media_wall.html
django_instagram/templatetags/__init__.py
django_instagram/templatetags/instagram_client.py
django_instagram-0.3.2.dist-info/LICENSE
django_instagram-0.3.2.dist-info/METADATA
django_instagram-0.3.2.dist-info/WHEEL
django_instagram-0.3.2.dist-info/top_level.txt
django_instagram-0.3.2.dist-info/RECORD
