Metadata-Version: 2.1
Name: django-instagram
Version: 0.3.2
Summary: Instagram client for Django.
Home-page: https://github.com/marcopompili/django-instagram
Author: Marco Pompili
Author-email: django@mg.odd.red
License: BSD-3 License
Platform: UNKNOWN
Classifier: Development Status :: 3 - Alpha
Classifier: Environment :: Web Environment
Classifier: Intended Audience :: Developers
Classifier: License :: OSI Approved :: BSD License
Classifier: Operating System :: OS Independent
Classifier: Programming Language :: Python
Classifier: Programming Language :: Python :: 3.3
Classifier: Programming Language :: Python :: 3.4
Classifier: Programming Language :: Python :: 3.5
Classifier: Programming Language :: Python :: 3.6
Classifier: Programming Language :: Python :: 3.7
Classifier: Topic :: Internet :: WWW/HTTP :: Dynamic Content
Classifier: Framework :: Django
Classifier: Framework :: Django :: 1.11
Classifier: Framework :: Django :: 2.0
Classifier: Framework :: Django :: 2.1
Classifier: Framework :: Django :: 2.2
Classifier: Framework :: Django :: 3.0
Requires-Dist: django (>=1.11)
Requires-Dist: lxml
Requires-Dist: requests
Requires-Dist: sorl-thumbnail
Requires-Dist: Pillow
